hitoshura25_mcp_server_generator/__init__.py
hitoshura25_mcp_server_generator/cli.py
hitoshura25_mcp_server_generator/generator.py
hitoshura25_mcp_server_generator/git_utils.py
hitoshura25_mcp_server_generator/server.py
hitoshura25_mcp_server_generator/templates/python/.gitignore.j2
hitoshura25_mcp_server_generator/templates/python/LICENSE.j2
hitoshura25_mcp_server_generator/templates/python/MANIFEST.in.j2
hitoshura25_mcp_server_generator/templates/python/MCP-USAGE.md.j2
hitoshura25_mcp_server_generator/templates/python/README.md.j2
hitoshura25_mcp_server_generator/templates/python/__init__.py.j2
hitoshura25_mcp_server_generator/templates/python/cli.py.j2
hitoshura25_mcp_server_generator/templates/python/generator.py.j2
hitoshura25_mcp_server_generator/templates/python/pyproject.toml.j2
hitoshura25_mcp_server_generator/templates/python/server.py.j2
hitoshura25_mcp_server_generator/templates/python/setup.py.j2
hitoshura25_mcp_server_generator/templates/python/tests/__init__.py.j2
hitoshura25_mcp_server_generator/templates/python/tests/test_generator.py.j2
hitoshura25_mcp_server_generator/templates/python/tests/test_server.py.j2
hitoshura25_mcp_server_generator/tests/__init__.py
hitoshura25_mcp_server_generator/tests/test_cli.py
hitoshura25_mcp_server_generator/tests/test_generator.py
hitoshura25_mcp_server_generator/tests/test_git_utils.py
hitoshura25_mcp_server_generator/tests/test_server.py
hitoshura25_mcp_server_generator/tests/test_templates.py
hitoshura25_mcp_server_generator-0.5.0.dist-info/licenses/LICENSE
hitoshura25_mcp_server_generator-0.5.0.dist-info/METADATA
hitoshura25_mcp_server_generator-0.5.0.dist-info/WHEEL
hitoshura25_mcp_server_generator-0.5.0.dist-info/entry_points.txt
hitoshura25_mcp_server_generator-0.5.0.dist-info/top_level.txt
hitoshura25_mcp_server_generator-0.5.0.dist-info/RECORD
