Metadata-Version: 2.4
Name: hitoshura25-mcp-server-generator
Version: 0.5.0
Summary: Generate dual-mode MCP servers with best practices
Home-page: https://github.com/hitoshura25/mcp-server-generator
Author: Vinayak Menon
Author-email: Vinayak Menon <vinayakmenon+pypi@users.noreply.github.com>
License: Apache-2.0
Project-URL: Homepage, https://github.com/hitoshura25/mcp-server-generator
Project-URL: Repository, https://github.com/hitoshura25/mcp-server-generator
Project-URL: Issues, https://github.com/hitoshura25/mcp-server-generator/issues
Classifier: Development Status :: 3 - Alpha
Classifier: Intended Audience :: Developers
Classifier: License :: OSI Approved :: Apache Software License
Classifier: Programming Language :: Python :: 3
Classifier: Programming Language :: Python :: 3.10
Classifier: Programming Language :: Python :: 3.11
Classifier: Programming Language :: Python :: 3.12
Classifier: Programming Language :: Python :: 3.13
Requires-Python: >=3.8
License-File: LICENSE
Requires-Dist: Jinja2>=3.0
Requires-Dist: hitoshura25-pypi-workflow-generator>=0.5.0
Requires-Dist: mcp<2.0.0,>=1.0.0
Provides-Extra: test
Requires-Dist: pytest>=7.0.0; extra == "test"
Requires-Dist: pytest-asyncio>=0.21.0; extra == "test"
Provides-Extra: dev
Requires-Dist: hitoshura25-mcp-server-generator[test]; extra == "dev"
Requires-Dist: build>=0.10.0; extra == "dev"
Dynamic: author
Dynamic: home-page
Dynamic: license-file
Dynamic: requires-python
